odoo8_addon_purchase_order_import_ubl-8.0.1.0.0.99.dev6-nspkg.pth
odoo_addons/purchase_order_import_ubl/README.rst
odoo_addons/purchase_order_import_ubl/__init__.py
odoo_addons/purchase_order_import_ubl/__openerp__.py
odoo_addons/purchase_order_import_ubl/demo/demo_data.xml
odoo_addons/purchase_order_import_ubl/i18n/purchase_order_import_ubl.pot
odoo_addons/purchase_order_import_ubl/static/description/icon.png
odoo_addons/purchase_order_import_ubl/tests/__init__.py
odoo_addons/purchase_order_import_ubl/tests/test_ubl_order_import.py
odoo_addons/purchase_order_import_ubl/tests/files/quote-PO00004.pdf
odoo_addons/purchase_order_import_ubl/wizard/__init__.py
odoo_addons/purchase_order_import_ubl/wizard/purchase_order_import.py
odoo8_addon_purchase_order_import_ubl-8.0.1.0.0.99.dev6.dist-info/METADATA
odoo8_addon_purchase_order_import_ubl-8.0.1.0.0.99.dev6.dist-info/WHEEL
odoo8_addon_purchase_order_import_ubl-8.0.1.0.0.99.dev6.dist-info/namespace_packages.txt
odoo8_addon_purchase_order_import_ubl-8.0.1.0.0.99.dev6.dist-info/top_level.txt
odoo8_addon_purchase_order_import_ubl-8.0.1.0.0.99.dev6.dist-info/RECORD
